iceberg_penguins.search-0.3.1-py3.5-nspkg.pth
iceberg_penguins/search/data/__init__.py
iceberg_penguins/search/data/base_data_loader.py
iceberg_penguins/search/data/base_dataset.py
iceberg_penguins/search/data/image_folder.py
iceberg_penguins/search/data/png_dataset.py
iceberg_penguins/search/data/single_dataset.py
iceberg_penguins/search/data/v2weaklyanno_dataset.py
iceberg_penguins/search/data/v3weaklyanno_dataset.py
iceberg_penguins/search/data/weaklyanno_dataset.py
iceberg_penguins/search/data_processing/__init__.py
iceberg_penguins/search/data_processing/convert_all_to_RGB.py
iceberg_penguins/search/data_processing/create_training_data_from_PTSmask.py
iceberg_penguins/search/data_processing/create_training_data_from_excels.py
iceberg_penguins/search/data_processing/create_training_set.py
iceberg_penguins/search/data_processing/dataset_create.py
iceberg_penguins/search/data_processing/gen_trainingpatches.py
iceberg_penguins/search/data_processing/im_vis.py
iceberg_penguins/search/data_processing/m_im_util.py
iceberg_penguins/search/data_processing/m_shape_util.py
iceberg_penguins/search/data_processing/split_train_test.py
iceberg_penguins/search/data_processing/tif_handle.py
iceberg_penguins/search/models/__init__.py
iceberg_penguins/search/models/base_model.py
iceberg_penguins/search/models/networks.py
iceberg_penguins/search/models/resnet18.py
iceberg_penguins/search/models/resnet18c_model.py
iceberg_penguins/search/models/unet_model.py
iceberg_penguins/search/models/unetr_model.py
iceberg_penguins/search/models/unetrd_model.py
iceberg_penguins/search/options/__init__.py
iceberg_penguins/search/options/base_options.py
iceberg_penguins/search/options/test_options.py
iceberg_penguins/search/options/train_options.py
iceberg_penguins/search/predicting/__init__.py
iceberg_penguins/search/predicting/predict.py
iceberg_penguins/search/predicting/resnet_predict.py
iceberg_penguins/search/util/__init__.py
iceberg_penguins/search/util/get_data.py
iceberg_penguins.search-0.3.1.dist-info/LICENSE.md
iceberg_penguins.search-0.3.1.dist-info/METADATA
iceberg_penguins.search-0.3.1.dist-info/WHEEL
iceberg_penguins.search-0.3.1.dist-info/namespace_packages.txt
iceberg_penguins.search-0.3.1.dist-info/top_level.txt
iceberg_penguins.search-0.3.1.dist-info/RECORD
