Metadata-Version: 2.1
Name: iceberg-penguins.search
Version: 0.3.1
Summary: The ICEBERG Penguin colony usecase package
Home-page: https://www.github.com/iceberg-project/Penguins/
Author: ICEBERG Team
Author-email: iceberg-ci@googlegroups.com
License: MIT
Platform: UNKNOWN
Classifier: Development Status :: 1 - Planning
Classifier: Intended Audience :: Developers
Classifier: Environment :: Console
Classifier: Programming Language :: Python
Classifier: Programming Language :: Python :: 3
Classifier: Programming Language :: Python :: 3.5
Classifier: Topic :: Utilities
Classifier: Topic :: Scientific/Engineering
Classifier: Operating System :: MacOS :: MacOS X
Classifier: Operating System :: POSIX
Classifier: Operating System :: Unix
Requires-Dist: scipy (==1.2.1)
Requires-Dist: Pillow (>=6.2.2)
Requires-Dist: torch
Requires-Dist: scikit-learn (==0.19.1)
Requires-Dist: torchvision (==0.2.0)
Requires-Dist: opencv-python
Requires-Dist: rasterio
Requires-Dist: imageio
Requires-Dist: future
